seen/SeeN_ZaN_XCODER2.py
seen/__init__.py
ajab-1.1.9.dist-info/METADATA
ajab-1.1.9.dist-info/WHEEL
ajab-1.1.9.dist-info/top_level.txt
ajab-1.1.9.dist-info/RECORD
